{"working_dir":null,"default_chunk_options":{"echo":true},"chunk_definitions":[{"row":9,"row_count":1,"visible":true,"expansion_state":0,"options":{"engine":"r","label":"setup","include":false},"document_id":"8F8B62C6","chunk_id":"csetup_chunk","chunk_label":"setup"},{"row":18,"row_count":1,"visible":true,"expansion_state":0,"options":{"engine":"r","label":"unnamed-chunk-1"},"document_id":"8F8B62C6","chunk_id":"cu05j4e7is8yf","chunk_label":"unnamed-chunk-1"},{"row":25,"row_count":1,"visible":true,"expansion_state":0,"options":{"engine":"r","label":"unnamed-chunk-2"},"document_id":"8F8B62C6","chunk_id":"ct0f23t1b2q3f","chunk_label":"unnamed-chunk-2"},{"row":32,"row_count":1,"visible":true,"expansion_state":0,"options":{"engine":"r","label":"unnamed-chunk-3"},"document_id":"8F8B62C6","chunk_id":"c2oid0i9crqhf","chunk_label":"unnamed-chunk-3"},{"row":50,"row_count":1,"visible":true,"expansion_state":0,"options":{"engine":"r","label":"unnamed-chunk-4"},"document_id":"8F8B62C6","chunk_id":"c3adyblijzv86","chunk_label":"unnamed-chunk-4"},{"row":60,"row_count":1,"visible":true,"expansion_state":0,"options":{"engine":"r","label":"unnamed-chunk-5"},"document_id":"8F8B62C6","chunk_id":"czaduro6la8n7","chunk_label":"unnamed-chunk-5"},{"row":70,"row_count":1,"visible":true,"expansion_state":0,"options":{"engine":"r","label":"unnamed-chunk-6"},"document_id":"8F8B62C6","chunk_id":"c31mfey0ha3al","chunk_label":"unnamed-chunk-6"},{"row":105,"row_count":1,"visible":true,"expansion_state":0,"options":{"engine":"r","label":"unnamed-chunk-7"},"document_id":"8F8B62C6","chunk_id":"c9tlhoa4kcvcy","chunk_label":"unnamed-chunk-7"},{"row":112,"row_count":1,"visible":true,"expansion_state":0,"options":{"engine":"r","label":"unnamed-chunk-8"},"document_id":"8F8B62C6","chunk_id":"ccxapbp1j7gqs","chunk_label":"unnamed-chunk-8"},{"row":124,"row_count":1,"visible":true,"expansion_state":0,"options":{"engine":"r","label":"unnamed-chunk-9"},"document_id":"8F8B62C6","chunk_id":"ctd5vfblbcuhy","chunk_label":"unnamed-chunk-9"},{"row":136,"row_count":1,"visible":true,"expansion_state":0,"options":{"engine":"r","label":"unnamed-chunk-10"},"document_id":"8F8B62C6","chunk_id":"ctkfoozbe8dq1","chunk_label":"unnamed-chunk-10"},{"row":145,"row_count":1,"visible":true,"expansion_state":0,"options":{"engine":"r","label":"unnamed-chunk-11"},"document_id":"8F8B62C6","chunk_id":"cjo8c5m3t56zg","chunk_label":"unnamed-chunk-11"},{"row":151,"row_count":1,"visible":true,"expansion_state":0,"options":{"engine":"r","label":"unnamed-chunk-12"},"document_id":"8F8B62C6","chunk_id":"cw6a1ubpu43ad","chunk_label":"unnamed-chunk-12"},{"row":164,"row_count":1,"visible":true,"expansion_state":0,"options":{"engine":"r","label":"unnamed-chunk-13"},"document_id":"8F8B62C6","chunk_id":"cv8np3kvhueei","chunk_label":"unnamed-chunk-13"},{"row":171,"row_count":1,"visible":true,"expansion_state":0,"options":{"engine":"r","label":"unnamed-chunk-14"},"document_id":"8F8B62C6","chunk_id":"crxsrc9i7vzc9","chunk_label":"unnamed-chunk-14"},{"row":180,"row_count":1,"visible":true,"expansion_state":0,"options":{"engine":"r","label":"unnamed-chunk-15"},"document_id":"8F8B62C6","chunk_id":"cuo6ou7ttfnhw","chunk_label":"unnamed-chunk-15"},{"row":188,"row_count":1,"visible":true,"expansion_state":0,"options":{"engine":"r","label":"unnamed-chunk-16"},"document_id":"8F8B62C6","chunk_id":"cp0kzdyhpfia6","chunk_label":"unnamed-chunk-16"},{"row":195,"row_count":1,"visible":true,"expansion_state":0,"options":{"engine":"r","label":"unnamed-chunk-17"},"document_id":"8F8B62C6","chunk_id":"cho3arkjq7x5f","chunk_label":"unnamed-chunk-17"},{"row":202,"row_count":1,"visible":true,"expansion_state":0,"options":{"engine":"r","label":"unnamed-chunk-18"},"document_id":"8F8B62C6","chunk_id":"cjydq8wcedd9x","chunk_label":"unnamed-chunk-18"},{"row":209,"row_count":1,"visible":true,"expansion_state":0,"options":{"engine":"r","label":"unnamed-chunk-19"},"document_id":"8F8B62C6","chunk_id":"ctf6mdlxonq42","chunk_label":"unnamed-chunk-19"},{"row":218,"row_count":1,"visible":true,"expansion_state":0,"options":{"engine":"r","label":"unnamed-chunk-20"},"document_id":"8F8B62C6","chunk_id":"cong4njg70vyo","chunk_label":"unnamed-chunk-20"},{"row":225,"row_count":1,"visible":true,"expansion_state":0,"options":{"engine":"r","label":"unnamed-chunk-21"},"document_id":"8F8B62C6","chunk_id":"ckx8w72t345ty","chunk_label":"unnamed-chunk-21"},{"row":234,"row_count":1,"visible":true,"expansion_state":0,"options":{"engine":"r","label":"unnamed-chunk-22"},"document_id":"8F8B62C6","chunk_id":"c5mft10aaayfi","chunk_label":"unnamed-chunk-22"},{"row":241,"row_count":1,"visible":true,"expansion_state":0,"options":{"engine":"r","label":"unnamed-chunk-23"},"document_id":"8F8B62C6","chunk_id":"c4aynzq22zf3c","chunk_label":"unnamed-chunk-23"},{"row":250,"row_count":1,"visible":true,"expansion_state":0,"options":{"engine":"r","label":"unnamed-chunk-24"},"document_id":"8F8B62C6","chunk_id":"cowf04x4ptsbk","chunk_label":"unnamed-chunk-24"},{"row":259,"row_count":1,"visible":true,"expansion_state":0,"options":{"engine":"r","label":"unnamed-chunk-25"},"document_id":"8F8B62C6","chunk_id":"c31j6io8we2ur","chunk_label":"unnamed-chunk-25"},{"row":269,"row_count":1,"visible":true,"expansion_state":0,"options":{"engine":"r","label":"unnamed-chunk-26"},"document_id":"8F8B62C6","chunk_id":"cqnnq1vb7fnit","chunk_label":"unnamed-chunk-26"},{"row":277,"row_count":1,"visible":true,"expansion_state":0,"options":{"engine":"r","label":"unnamed-chunk-27"},"document_id":"8F8B62C6","chunk_id":"c15fz9nscl6gw","chunk_label":"unnamed-chunk-27"},{"row":286,"row_count":1,"visible":true,"expansion_state":0,"options":{"engine":"r","label":"unnamed-chunk-28"},"document_id":"8F8B62C6","chunk_id":"cb5cb284dfhbh","chunk_label":"unnamed-chunk-28"},{"row":292,"row_count":1,"visible":true,"expansion_state":0,"options":{"engine":"r","label":"unnamed-chunk-29"},"document_id":"8F8B62C6","chunk_id":"cooagw5an2zbe","chunk_label":"unnamed-chunk-29"},{"row":297,"row_count":1,"visible":true,"expansion_state":0,"options":{"engine":"r","label":"unnamed-chunk-30"},"document_id":"8F8B62C6","chunk_id":"ck98jookd35fg","chunk_label":"unnamed-chunk-30"},{"row":303,"row_count":1,"visible":true,"expansion_state":0,"options":{"engine":"r","label":"unnamed-chunk-31"},"document_id":"8F8B62C6","chunk_id":"coenyrrfvlut3","chunk_label":"unnamed-chunk-31"},{"row":312,"row_count":1,"visible":true,"expansion_state":0,"options":{"engine":"r","label":"unnamed-chunk-32"},"document_id":"8F8B62C6","chunk_id":"cqoz7sy17wbmc","chunk_label":"unnamed-chunk-32"},{"row":318,"row_count":1,"visible":true,"expansion_state":0,"options":{"engine":"r","label":"unnamed-chunk-33"},"document_id":"8F8B62C6","chunk_id":"c5enciojit1xm","chunk_label":"unnamed-chunk-33"},{"row":323,"row_count":1,"visible":true,"expansion_state":0,"options":{"engine":"r","label":"unnamed-chunk-34"},"document_id":"8F8B62C6","chunk_id":"c7piw54sww26j","chunk_label":"unnamed-chunk-34"},{"row":336,"row_count":1,"visible":true,"expansion_state":0,"options":{"engine":"r","label":"unnamed-chunk-35"},"document_id":"8F8B62C6","chunk_id":"c9p1u9kdf2ya5","chunk_label":"unnamed-chunk-35"},{"row":344,"row_count":1,"visible":true,"expansion_state":0,"options":{"engine":"r","label":"unnamed-chunk-36"},"document_id":"8F8B62C6","chunk_id":"c6wry39bgn5qr","chunk_label":"unnamed-chunk-36"},{"row":352,"row_count":1,"visible":true,"expansion_state":0,"options":{"engine":"r","label":"unnamed-chunk-37"},"document_id":"8F8B62C6","chunk_id":"cmjao9zpe7s8o","chunk_label":"unnamed-chunk-37"},{"row":361,"row_count":1,"visible":true,"expansion_state":0,"options":{"engine":"r","label":"unnamed-chunk-38"},"document_id":"8F8B62C6","chunk_id":"cw9q9x6rreqcz","chunk_label":"unnamed-chunk-38"},{"row":372,"row_count":1,"visible":true,"expansion_state":0,"options":{"engine":"r","label":"unnamed-chunk-39"},"document_id":"8F8B62C6","chunk_id":"cnutoyvpnl3pm","chunk_label":"unnamed-chunk-39"},{"row":383,"row_count":1,"visible":true,"expansion_state":0,"options":{"engine":"r","label":"unnamed-chunk-40"},"document_id":"8F8B62C6","chunk_id":"cjo5hf78xiewv","chunk_label":"unnamed-chunk-40"},{"row":395,"row_count":1,"visible":true,"expansion_state":0,"options":{"engine":"r","label":"unnamed-chunk-41"},"document_id":"8F8B62C6","chunk_id":"cryl3f48bdz7x","chunk_label":"unnamed-chunk-41"},{"row":403,"row_count":1,"visible":true,"expansion_state":0,"options":{"engine":"r","label":"unnamed-chunk-42"},"document_id":"8F8B62C6","chunk_id":"cv00ite606tsa","chunk_label":"unnamed-chunk-42"},{"row":409,"row_count":1,"visible":true,"expansion_state":0,"options":{"engine":"r","label":"unnamed-chunk-43"},"document_id":"8F8B62C6","chunk_id":"c2ybeb4zvd3kl","chunk_label":"unnamed-chunk-43"},{"row":413,"row_count":1,"visible":true,"expansion_state":0,"options":{"engine":"r","label":"unnamed-chunk-44"},"document_id":"8F8B62C6","chunk_id":"c3s2hw5ilst4x","chunk_label":"unnamed-chunk-44"},{"row":421,"row_count":1,"visible":true,"expansion_state":0,"options":{"engine":"r","label":"unnamed-chunk-45"},"document_id":"8F8B62C6","chunk_id":"cjngbo6vje7lu","chunk_label":"unnamed-chunk-45"},{"row":430,"row_count":1,"visible":true,"expansion_state":0,"options":{"engine":"r","label":"unnamed-chunk-46"},"document_id":"8F8B62C6","chunk_id":"cg7ha59apsq78","chunk_label":"unnamed-chunk-46"},{"row":437,"row_count":1,"visible":true,"expansion_state":0,"options":{"engine":"r","label":"unnamed-chunk-47"},"document_id":"8F8B62C6","chunk_id":"co591tv2vq3vj","chunk_label":"unnamed-chunk-47"},{"row":446,"row_count":1,"visible":true,"expansion_state":0,"options":{"engine":"r","label":"unnamed-chunk-48"},"document_id":"8F8B62C6","chunk_id":"c1rlc66rudwjt","chunk_label":"unnamed-chunk-48"},{"row":454,"row_count":1,"visible":true,"expansion_state":0,"options":{"engine":"r","label":"unnamed-chunk-49"},"document_id":"8F8B62C6","chunk_id":"ce19ohwkb93lk","chunk_label":"unnamed-chunk-49"},{"row":461,"row_count":1,"visible":true,"expansion_state":0,"options":{"engine":"r","label":"unnamed-chunk-50"},"document_id":"8F8B62C6","chunk_id":"ckn57u8936pnl","chunk_label":"unnamed-chunk-50"},{"row":467,"row_count":1,"visible":true,"expansion_state":0,"options":{"engine":"r","label":"unnamed-chunk-51"},"document_id":"8F8B62C6","chunk_id":"cnwsl74jm5ejn","chunk_label":"unnamed-chunk-51"},{"row":475,"row_count":1,"visible":true,"expansion_state":0,"options":{"engine":"r","label":"unnamed-chunk-52"},"document_id":"8F8B62C6","chunk_id":"cl6zkm22sgzpo","chunk_label":"unnamed-chunk-52"},{"row":485,"row_count":1,"visible":true,"expansion_state":0,"options":{"engine":"r","label":"unnamed-chunk-53"},"document_id":"8F8B62C6","chunk_id":"cjlhcq9jvp6qi","chunk_label":"unnamed-chunk-53"},{"row":496,"row_count":1,"visible":true,"expansion_state":0,"options":{"engine":"r","label":"unnamed-chunk-54"},"document_id":"8F8B62C6","chunk_id":"cdlqf2ddahpz0","chunk_label":"unnamed-chunk-54"},{"row":503,"row_count":1,"visible":true,"expansion_state":0,"options":{"engine":"r","label":"unnamed-chunk-55"},"document_id":"8F8B62C6","chunk_id":"c4f7ricv6lobl","chunk_label":"unnamed-chunk-55"},{"row":512,"row_count":1,"visible":true,"expansion_state":0,"options":{"engine":"r","label":"unnamed-chunk-56"},"document_id":"8F8B62C6","chunk_id":"cgmfrtjiln4rr","chunk_label":"unnamed-chunk-56"},{"row":531,"row_count":1,"visible":true,"expansion_state":0,"options":{"engine":"r","message":false,"label":"unnamed-chunk-57"},"document_id":"8F8B62C6","chunk_id":"ck5n8rg25u4sw","chunk_label":"unnamed-chunk-57"},{"row":538,"row_count":1,"visible":true,"expansion_state":0,"options":{"engine":"r","label":"unnamed-chunk-58"},"document_id":"8F8B62C6","chunk_id":"czs4zultv7tqf","chunk_label":"unnamed-chunk-58"},{"row":562,"row_count":1,"visible":true,"expansion_state":0,"options":{"engine":"r","label":"unnamed-chunk-59"},"document_id":"8F8B62C6","chunk_id":"ci0ky83chnz69","chunk_label":"unnamed-chunk-59"},{"row":577,"row_count":1,"visible":true,"expansion_state":0,"options":{},"document_id":"8F8B62C6","chunk_id":"c6u47y863t3pu","chunk_label":"unnamed-chunk-61"},{"row":583,"row_count":1,"visible":true,"expansion_state":0,"options":{},"document_id":"8F8B62C6","chunk_id":"cpw2lp5xwgu4f","chunk_label":"unnamed-chunk-62"}],"doc_write_time":1635941440,"chunk_rendered_width":700}